flask_dictabase/__init__.py
flask_dictabase-1.2.5.dist-info/METADATA
flask_dictabase-1.2.5.dist-info/WHEEL
flask_dictabase-1.2.5.dist-info/top_level.txt
flask_dictabase-1.2.5.dist-info/RECORD
